{"errors":[],"warnings":[],"namedChunkGroups":{"app":{"chunks":[6,4,1],"assets":["webpack-runtime-773579f295ff42e6e819.js","webpack-runtime-773579f295ff42e6e819.js.map","framework-16534ddc5a576711dd15.js","framework-16534ddc5a576711dd15.js.map","app-52564ec0d93a26ee84a4.js","app-52564ec0d93a26ee84a4.js.map"],"children":{},"childAssets":{}},"component---src-pages-404-js":{"chunks":[0,2],"assets":["commons-3452bb3ee38b41622521.js","commons-3452bb3ee38b41622521.js.map","component---src-pages-404-js-608ca0b7a8185d6ebb62.js","component---src-pages-404-js-608ca0b7a8185d6ebb62.js.map"],"children":{},"childAssets":{}},"component---src-pages-index-js":{"chunks":[5,0,3],"assets":["styles.d5d8baa2b973a6fd5f38.css","styles-2c8cc638826070126d54.js","styles-2c8cc638826070126d54.js.map","commons-3452bb3ee38b41622521.js","commons-3452bb3ee38b41622521.js.map","component---src-pages-index-js-bd2c52b5ca3a7eefc66f.js","component---src-pages-index-js-bd2c52b5ca3a7eefc66f.js.map"],"children":{},"childAssets":{}}},"assetsByChunkName":{"app":["webpack-runtime-773579f295ff42e6e819.js","framework-16534ddc5a576711dd15.js","app-52564ec0d93a26ee84a4.js"],"component---src-pages-404-js":["commons-3452bb3ee38b41622521.js","component---src-pages-404-js-608ca0b7a8185d6ebb62.js"],"component---src-pages-index-js":["styles.d5d8baa2b973a6fd5f38.css","styles-2c8cc638826070126d54.js","commons-3452bb3ee38b41622521.js","component---src-pages-index-js-bd2c52b5ca3a7eefc66f.js"]}}